mkite_engines/__init__.py
mkite_engines/base.py
mkite_engines/instantiate.py
mkite_engines/local.py
mkite_engines/redis.py
mkite_engines/settings.py
mkite_engines/cli/__init__.py
mkite_engines/cli/kiteng.py
mkite_engines/cli/redis.py
mkite_engines/tests/__init__.py
mkite_engines/tests/test_instantiate.py
mkite_engines/tests/test_redis.py
mkite_engines/tests/configs/__init__.py
mkite_engines/tests/configs/local.yaml
mkite_engines-25.11.3.dist-info/licenses/LICENSE
mkite_engines-25.11.3.dist-info/licenses/NOTICE
mkite_engines-25.11.3.dist-info/METADATA
mkite_engines-25.11.3.dist-info/WHEEL
mkite_engines-25.11.3.dist-info/entry_points.txt
mkite_engines-25.11.3.dist-info/top_level.txt
mkite_engines-25.11.3.dist-info/RECORD
