Metadata-Version: 2.4
Name: mkite_engines
Version: 25.11.3
Summary: engines for connecting messages to/from mkite
Author-email: Daniel Schwalbe-Koda <dskoda@ucla.edu>
Keywords: workflow,materials-science
Requires-Python: >=3.8
License-File: LICENSE
License-File: NOTICE
Requires-Dist: pydantic>=2.0
Requires-Dist: redis
Requires-Dist: fakeredis
Dynamic: license-file
